README.md
setup.py
pocket_tagger/__init__.py
pocket_tagger/language_service_client.py
pocket_tagger/logger.py
pocket_tagger/pocket_api_client.py
pocket_tagger/pocket_tagger.py
pocket_tagger/scraper.py
pocket_tagger.egg-info/PKG-INFO
pocket_tagger.egg-info/SOURCES.txt
pocket_tagger.egg-info/dependency_links.txt
pocket_tagger.egg-info/requires.txt
pocket_tagger.egg-info/top_level.txt