Metadata-Version: 2.1
Name: pocket-tagger
Version: 0.1.1
Summary: Tag your pocket articles from getpocket.com automatically using NLP
Home-page: http://github.com/sanghviharshit/pocket-tagger
Author: Harshit Sanghvi
Author-email: hello@sanghviharshit.com
License: MIT
Project-URL: Bug Reports, https://github.com/sanghviharshit/pocket-tagger/issues
Project-URL: Say Thanks!, https://saythanks.io/to/sanghviharshit
Project-URL: Source, https://github.com/sanghviharshit/pocket-tagger
Keywords: getpocket,pocket,api,articles,automatic,suggested,tag,natural language processing,nlp
Platform: UNKNOWN
Classifier: Development Status :: 4 - Beta
Classifier: Intended Audience :: Developers
Classifier: Intended Audience :: End Users/Desktop
Classifier: Operating System :: OS Independent
Classifier: Topic :: Software Development :: Libraries :: Python Modules
Classifier: License :: OSI Approved :: MIT License
Classifier: Programming Language :: Python :: 3
Classifier: Programming Language :: Python :: 3.4
Classifier: Programming Language :: Python :: 3.5
Classifier: Programming Language :: Python :: 3.6
Classifier: Programming Language :: Python :: 3.7
